mlplumber/__init__.py
mlplumber/pandas_adapter.py
mlplumber/steps.py
mlplumber/transformers.py
mlplumber-0.1.43.dist-info/LICENSE
mlplumber-0.1.43.dist-info/METADATA
mlplumber-0.1.43.dist-info/WHEEL
mlplumber-0.1.43.dist-info/top_level.txt
mlplumber-0.1.43.dist-info/RECORD
